plus/__init__.py
plus/plus.py
pluspy-0.0.3.dist-info/LICENSE
pluspy-0.0.3.dist-info/METADATA
pluspy-0.0.3.dist-info/WHEEL
pluspy-0.0.3.dist-info/top_level.txt
pluspy-0.0.3.dist-info/RECORD
