Metadata-Version: 2.1
Name: pluspy
Version: 0.0.3
Summary: For all your adding needs, up to numbers of 250.
Home-page: https://github.com/stijndcl/plus
Author: stijndcl
Author-email: declercq.stijn@outlook.com
License: UNKNOWN
Platform: UNKNOWN
Classifier: Programming Language :: Python :: 3
Classifier: License :: OSI Approved :: MIT License
Classifier: Operating System :: OS Independent
Requires-Python: >=3.6
